img_ai/__init__.py
img_ai-1.0.dist-info/METADATA
img_ai-1.0.dist-info/WHEEL
img_ai-1.0.dist-info/top_level.txt
img_ai-1.0.dist-info/RECORD
