Metadata-Version: 2.1
Name: img_ai
Version: 1.0
Summary: This library is an advanced artificial intelligence to help with advanced and fast software and solutions
Home-page: https://github.com/mr-sami-x/image_ai
Author: SamiSoft - Yemen
Classifier: Programming Language :: Python :: 3
Classifier: License :: OSI Approved :: MIT License
Classifier: Operating System :: OS Independent
Requires-Python: >=3.6
Requires-Dist: requests
